AUTHORS.rst
CONTRIBUTING.rst
HISTORY.rst
LICENSE
MANIFEST.in
README.rst
setup.cfg
setup.py
django_newsletter2go.egg-info/PKG-INFO
django_newsletter2go.egg-info/SOURCES.txt
django_newsletter2go.egg-info/dependency_links.txt
django_newsletter2go.egg-info/not-zip-safe
django_newsletter2go.egg-info/top_level.txt
newsletter2go/__init__.py
newsletter2go/backends.py
newsletter2go/models.py