Metadata-Version: 1.1
Name: django-newsletter2go
Version: 0.1.0
Summary: An email backend for Django that uses Newsletter2Go transactional emails
Home-page: https://github.com/productgang/django-newsletter2go
Author: Lukas Klein
Author-email: lukas@productgang.com
License: BSD
Keywords: django-newsletter2go
Platform: UNKNOWN
Classifier: Development Status :: 2 - Pre-Alpha
Classifier: Framework :: Django
Classifier: Intended Audience :: Developers
Classifier: License :: OSI Approved :: BSD License
Classifier: Natural Language :: English
Classifier: Programming Language :: Python :: 2
Classifier: Programming Language :: Python :: 2.7
Classifier: Programming Language :: Python :: 3
Classifier: Programming Language :: Python :: 3.3
Classifier: Programming Language :: Python :: 3.4
